{"py/object": "rasa.core.featurizers.tracker_featurizers.MaxHistoryTrackerFeaturizer", "state_featurizer": {"py/object": "rasa.core.featurizers.single_state_featurizer.SingleStateFeaturizer", "_default_feature_states": {"intent": {"ask_about_adaptability": 0, "ask_about_all_faculties": 1, "ask_about_all_programs": 2, "ask_about_capabilities": 3, "ask_about_ethics": 4, "ask_about_limitations": 5, "ask_about_mission": 6, "ask_about_program_fees": 7, "ask_about_program_requirements": 8, "ask_about_program_selection": 9, "ask_about_role": 10, "ask_about_specific_faculty": 11, "ask_about_specific_faculty_programs": 12, "ask_about_specific_program": 13, "ask_about_specific_social_media": 14, "ask_about_tone": 15, "ask_about_university_address": 16, "ask_about_university_contact": 17, "ask_about_university_general": 18, "ask_about_university_phone": 19, "ask_about_university_website": 20, "ask_about_value_symbol": 21, "ask_about_yucca_character": 22, "ask_about_yucca_connection": 23, "ask_about_yucca_symbolism": 24, "ask_about_yucca_values": 25, "back": 26, "nlu_fallback": 27, "out_of_scope": 28, "restart": 29, "session_start": 30}, "action_name": {"action_listen": 0, "action_restart": 1, "action_session_start": 2, "action_default_fallback": 3, "action_deactivate_loop": 4, "action_revert_fallback_events": 5, "action_default_ask_affirmation": 6, "action_default_ask_rephrase": 7, "action_two_stage_fallback": 8, "action_unlikely_intent": 9, "action_back": 10, "...": 11, "action_extract_slots": 12, "action_handle_out_of_scope": 13, "action_fetch_value_lambang": 14, "action_fetch_mission": 15, "action_provide_university_contact": 16, "action_provide_social_media": 17, "action_provide_university_info": 18, "action_provide_faculty_details": 19, "action_provide_all_programs": 20, "action_provide_program_details": 21, "action_provide_faculty_programs": 22, "action_provide_program_requirements": 23, "action_provide_program_selection": 24, "action_provide_program_fees": 25, "utter_about_adaptability": 26, "utter_about_all_faculties": 27, "utter_about_capabilities": 28, "utter_about_ethics": 29, "utter_about_limitations": 30, "utter_about_role": 31, "utter_about_university_address": 32, "utter_about_university_contact": 33, "utter_about_university_general": 34, "utter_about_university_phone": 35, "utter_about_university_website": 36, "utter_about_yucca_character": 37, "utter_about_yucca_connection": 38, "utter_about_yucca_symbolism": 39, "utter_about_yucca_values": 40, "utter_all_programs": 41, "utter_faculty_not_found": 42, "utter_out_of_scope": 43, "utter_program_not_found": 44}, "entities": {"kode_fakultas": 0, "kode_program_studi": 1, "platform": 2, "value": 3}, "slots": {"platform_0": 0, "value_0": 1, "kode_fakultas_0": 2, "kode_program_studi_0": 3}, "active_loop": {}}, "action_texts": [], "entity_tag_specs": []}, "max_history": 5, "remove_duplicates": true}